setup.py
src/helloljj_0.1.1.egg-info/PKG-INFO
src/helloljj_0.1.1.egg-info/SOURCES.txt
src/helloljj_0.1.1.egg-info/dependency_links.txt
src/helloljj_0.1.1.egg-info/top_level.txt
src/ljj/__init__.py
src/ljj/handsome/__init__.py
src/ljj/handsome/boy/__init__.py
src/ljj/handsome/boy/message.py