Metadata-Version: 2.1
Name: helloljj-0.1.1
Version: 0.1.1
Summary: the team 's member just only one  
Home-page: UNKNOWN
Author: ljj
Author-email: 1498283571@qq.com
License: UNKNOWN
Platform: UNKNOWN
